d5m_ai/__init__.py
d5m_ai/_version.py
d5m_ai/extension.py
d5m_ai/git_status_handler.py
d5m_ai/gitignore_handler.py
d5m_ai/search_replace_handler.py
d5m_ai/agent/__init__.py
d5m_ai/agent/config.py
d5m_ai/agent/image_processor.py
d5m_ai/agent/proxy_handler.py
d5m_ai/agent/tool_registry.py
d5m_ai/agent/websocket_tool_executor.py
d5m_ai/agent/tools/__init__.py
d5m_ai/agent/tools/frontend/__init__.py
d5m_ai/agent/tools/frontend/cell_ops.py
d5m_ai/agent/tools/frontend/helpers.py
d5m_ai/agent/tools/frontend/notebook.py
d5m_ai/agent/tools/local/__init__.py
d5m_ai/agent/tools/local/file_ops.py
d5m_ai/agent/tools/local/search.py
d5m_ai/agent/tools/local/shell.py
d5m_ai/auth/__init__.py
d5m_ai/auth/token_handler.py
d5m_ai/chat/__init__.py
d5m_ai/chat/chat_proxy_handler.py
d5m_ai/chat/code_apply.py
d5m_ai/chat/history.py
d5m_ai/completion/__init__.py
d5m_ai/completion/handler.py
d5m_ai/edit/__init__.py
d5m_ai/edit/config.py
d5m_ai/edit/connection_manager.py
d5m_ai/edit/edit_proxy_handler.py
d5m_ai/edit/image_processor.py
d5m_ai/edit/shell_executor.py
d5m_ai/empty_display/__init__.py
d5m_ai/empty_display/empty_display_handler.py
d5m_ai/image/__init__.py
d5m_ai/image/handler.py
d5m_ai/labextension/package.json
d5m_ai/labextension/schemas/runcell/file-browser-toggle.json
d5m_ai/labextension/schemas/runcell/package.json.orig
d5m_ai/labextension/schemas/runcell/plugin.json
d5m_ai/labextension/static/1045.a76db59a7c20953976f0.js
d5m_ai/labextension/static/1055.87aafb19805530488a2c.js
d5m_ai/labextension/static/108.d7dbe40ec7e0ae1a68f8.js
d5m_ai/labextension/static/1104.a2b939bacec5e69efd99.js
d5m_ai/labextension/static/1105.da3b3cc0801d5b7daf78.js
d5m_ai/labextension/static/1113.a6206c1ce30c44e74d65.js
d5m_ai/labextension/static/1171.130d3cc54764cac92856.js
d5m_ai/labextension/static/1178.3e25fad4a45450e227c9.js
d5m_ai/labextension/static/1203.5deaeee9e57ffc718f19.js
d5m_ai/labextension/static/1226.ff48aa5741f77eb739fe.js
d5m_ai/labextension/static/1273.4c5992b03f129c9e3025.js
runcell-0.1.16.post1.dist-info/METADATA
runcell-0.1.16.post1.dist-info/WHEEL
runcell-0.1.16.post1.dist-info/entry_points.txt
runcell-0.1.16.post1.dist-info/licenses/LICENSE
runcell-0.1.16.post1.dist-info/RECORD
