Metadata-Version: 2.4
Name: runcell
Version: 0.1.16.post1
Summary: AI Agent for Jupyter
Project-URL: homepage, https://www.runcell.dev
Author-email: Elwynn Chen <elwynn.c@kanaries.net>
License: BSD 3-Clause License
License-File: LICENSE
Keywords: jupyter,jupyterlab,jupyterlab-extension
Classifier: Framework :: Jupyter
Classifier: Framework :: Jupyter :: JupyterLab
Classifier: Framework :: Jupyter :: JupyterLab :: 4
Classifier: Framework :: Jupyter :: JupyterLab :: Extensions
Classifier: Framework :: Jupyter :: JupyterLab :: Extensions :: Prebuilt
Classifier: License :: OSI Approved :: BSD License
Classifier: Programming Language :: Python
Classifier: Programming Language :: Python :: 3
Classifier: Programming Language :: Python :: 3.9
Classifier: Programming Language :: Python :: 3.10
Classifier: Programming Language :: Python :: 3.11
Classifier: Programming Language :: Python :: 3.12
Classifier: Programming Language :: Python :: 3.13
Requires-Python: >=3.9
Requires-Dist: aiohttp
Requires-Dist: dill
Requires-Dist: ipython
Requires-Dist: jupyter-server
Requires-Dist: jupyter-server-documents>=0.1.0a9
Requires-Dist: matplotlib
Requires-Dist: numpy
Requires-Dist: openai
Requires-Dist: pandas
Requires-Dist: python-dotenv
Requires-Dist: python-socks
Requires-Dist: websockets
